pytest_reference_formatter/__init__.py
pytest_reference_formatter/formatter.py
pytest_reference_formatter-0.2.dist-info/METADATA
pytest_reference_formatter-0.2.dist-info/WHEEL
pytest_reference_formatter-0.2.dist-info/top_level.txt
pytest_reference_formatter-0.2.dist-info/RECORD
