Metadata-Version: 1.1
Name: pytest_reference_formatter
Version: 0.2
Summary: Conveniently run pytest with a dot-formatted test reference.
Home-page: https://github.com/PaesslerAG/pytest-reference-formatter
Author: Paessler AG
Author-email: bis@paessler.com
License: MIT
Keywords: pytest-reference-formatter
Platform: UNKNOWN
Classifier: Development Status :: 4 - Beta
Classifier: Intended Audience :: Developers
Classifier: License :: OSI Approved :: MIT License
Classifier: Natural Language :: English
Classifier: Programming Language :: Python :: 2
Classifier: Programming Language :: Python :: 2.7
Classifier: Programming Language :: Python :: 3
Classifier: Programming Language :: Python :: 3.5
Classifier: Programming Language :: Python :: 3.6
Classifier: Programming Language :: Python :: 3.7
